stanhelper/__init__.py
stanhelper/stanhelper.py
stanhelper-1.2.1.dist-info/LICENSE
stanhelper-1.2.1.dist-info/METADATA
stanhelper-1.2.1.dist-info/WHEEL
stanhelper-1.2.1.dist-info/top_level.txt
stanhelper-1.2.1.dist-info/RECORD
