Metadata-Version: 2.1
Name: stanhelper
Version: 1.2.1
Summary: Functions that help interface with cmdStan.
Home-page: https://github.com/akucukelbir/stanhelper
Download-URL: https://github.com/akucukelbir/stanhelper/releases/1.2.1
Author: Alp Kucukelbir
Author-email: alp@cs.columbia.edu
License: MIT
Requires-Python: >=3.5
License-File: LICENSE
Requires-Dist: pandas
